deeptorchblocks/Dense.py
deeptorchblocks/Inception.py
deeptorchblocks/Recurrent.py
deeptorchblocks/Residual.py
deeptorchblocks/Standard.py
deeptorchblocks/__init__.py
deeptorchblocks-0.1.0.dist-info/METADATA
deeptorchblocks-0.1.0.dist-info/WHEEL
deeptorchblocks-0.1.0.dist-info/RECORD
