Metadata-Version: 2.1
Name: deeptorchblocks
Version: 0.1.0
Summary: Pytorch high-level SoA building blocks
License: MIT
Author: Stefano Giacomelli
Author-email: stefano.giacomelli1992@gmail.com
Requires-Python: >=3.10,<4.0
Classifier: License :: OSI Approved :: MIT License
Classifier: Programming Language :: Python :: 3
Classifier: Programming Language :: Python :: 3.10
Classifier: Programming Language :: Python :: 3.11
Classifier: Programming Language :: Python :: 3.12
Requires-Dist: numpy (>=1.26.4,<2.0.0)
Requires-Dist: torch (>=2.2.2,<3.0.0)
